symgt/__init__.py
symgt/algorithms.py
symgt/models.py
symgt/py.typed
symgt/utils.py
symgt-0.0.18.dist-info/METADATA
symgt-0.0.18.dist-info/WHEEL
symgt-0.0.18.dist-info/RECORD
